MitmLibrary/__init__.py
MitmLibrary/async_loop_thread.py
MitmLibrary/request_logger.py
MitmLibrary/version.py
robotframework_mitmlibrary-0.2.2.dist-info/METADATA
robotframework_mitmlibrary-0.2.2.dist-info/WHEEL
robotframework_mitmlibrary-0.2.2.dist-info/RECORD
