Metadata-Version: 2.3
Name: robotframework-mitmlibrary
Version: 0.2.2
Summary: A Robot Framework library for managing and manipulating HTTP requests and responses using a man-in-the-middle proxy approach. It allows blocking requests, customizing responses, adding delays, and more.
License: MIT
Author: Mark
Author-email: markmoberts@gmail.com
Requires-Python: >=3.12,<4.0
Classifier: License :: OSI Approved :: MIT License
Classifier: Programming Language :: Python :: 3
Classifier: Programming Language :: Python :: 3.12
Classifier: Programming Language :: Python :: 3.13
Requires-Dist: mitmproxy (>=12.0.1,<13.0.0)
Requires-Dist: robotframework (>=7.1.1,<8.0.0)
Requires-Dist: wheel (>=0.45.1,<0.46.0)
Project-URL: Documentation, https://mobynl.github.io/robotframework-mitmlibrary/MitmLibraryKeywords.html
Project-URL: Homepage, https://github.com/MobyNL/robotframework-mitmlibrary
Project-URL: Repository, https://github.com/MobyNL/robotframework-mitmlibrary
